{
  "id": "kubeapt",
  "name": "kubeapt",
  "category_id": "devops",
  "category_name": "DevOps",
  "description": "The software may collect information about you and your use of the software.",
  "links": {
    "main": "https://github.com/twosson/kubeapt",
    "telemetry": "https://github.com/twosson/kubeapt#environment-variables"
  },
  "telemetry": [
    {
      "id": "usage-data",
      "name": "Usage data",
      "is_official": true,
      "target": {
        "env": {
          "scope": {
            "process": {
              "path": {
                "default": "DASH_DISABLE_TELEMETRY"
              },
              "value": {
                "opt_out": "ANY_VALUE",
                "opt_in": null
              }
            }
          }
        }
      }
    }
  ]
}